clarity_api/__init__.py
clarity_api/clarity_api.py
clarity_api/clarity_models.py
clarity_api/decorators.py
clarity_api/exceptions.py
clarity_api/utils.py
clarity_api/version.py
clarity_api-0.0.3.dist-info/LICENSE
clarity_api-0.0.3.dist-info/METADATA
clarity_api-0.0.3.dist-info/WHEEL
clarity_api-0.0.3.dist-info/top_level.txt
clarity_api-0.0.3.dist-info/RECORD
