Metadata-Version: 2.1
Name: clarity-api
Version: 0.0.3
Summary: Microsoft Clarity Data Export API
Home-page: https://github.com/Knuckles-Team/clarity-api
Author: Audel Rouhi
Author-email: knucklessg1@gmail.com
License: MIT
Platform: UNKNOWN
Classifier: Development Status :: 5 - Production/Stable
Classifier: License :: Public Domain
Classifier: Environment :: Console
Classifier: Operating System :: POSIX :: Linux
Classifier: Programming Language :: Python :: 3.8
Classifier: Programming Language :: Python :: 3.9
Classifier: Programming Language :: Python :: 3.10
Classifier: Programming Language :: Python :: 3.11
Classifier: Programming Language :: Python :: 3.12
License-File: LICENSE
Requires-Dist: pydantic[email] (>=2.8.2)
Requires-Dist: requests (>=2.8.1)
Requires-Dist: urllib3 (>=2.2.2)
